pnap_bmc_api/__init__.py
pnap_bmc_api/api_client.py
pnap_bmc_api/api_response.py
pnap_bmc_api/configuration.py
pnap_bmc_api/exceptions.py
pnap_bmc_api/py.typed
pnap_bmc_api/rest.py
pnap_bmc_api/version.py
pnap_bmc_api/api/__init__.py
pnap_bmc_api/api/quotas_api.py
pnap_bmc_api/api/servers_api.py
pnap_bmc_api/api/ssh_keys_api.py
pnap_bmc_api/models/__init__.py
pnap_bmc_api/models/action_result.py
pnap_bmc_api/models/delete_result.py
pnap_bmc_api/models/delete_ssh_key_result.py
pnap_bmc_api/models/error.py
pnap_bmc_api/models/esxi_datastore_configuration.py
pnap_bmc_api/models/esxi_os_configuration.py
pnap_bmc_api/models/gpu_configuration.py
pnap_bmc_api/models/ip_blocks_configuration.py
pnap_bmc_api/models/network_configuration.py
pnap_bmc_api/models/os_configuration.py
pnap_bmc_api/models/os_configuration_cloud_init.py
pnap_bmc_api/models/os_configuration_map.py
pnap_bmc_api/models/os_configuration_map_esxi.py
pnap_bmc_api/models/os_configuration_map_proxmox.py
pnap_bmc_api/models/os_configuration_netris_controller.py
pnap_bmc_api/models/os_configuration_netris_softgate.py
pnap_bmc_api/models/os_configuration_windows.py
pnap_bmc_api/models/private_network_configuration.py
pnap_bmc_api/models/public_network_configuration.py
pnap_bmc_api/models/quota.py
pnap_bmc_api/models/quota_edit_limit_request.py
pnap_bmc_api/models/quota_edit_limit_request_details.py
pnap_bmc_api/models/relinquish_ip_block.py
pnap_bmc_api/models/reset_result.py
pnap_bmc_api/models/server.py
pnap_bmc_api/models/server_create.py
pnap_bmc_api/models/server_ip_block.py
pnap_bmc_api/models/server_network_update.py
pnap_bmc_api/models/server_patch.py
pnap_bmc_api/models/server_private_network.py
pnap_bmc_api/models/server_provision.py
pnap_bmc_api/models/server_public_network.py
pnap_bmc_api/models/server_reserve.py
pnap_bmc_api/models/server_reset.py
pnap_bmc_api/models/ssh_key.py
pnap_bmc_api/models/ssh_key_create.py
pnap_bmc_api/models/ssh_key_update.py
pnap_bmc_api/models/storage_configuration.py
pnap_bmc_api-2.2.1.dist-info/METADATA
pnap_bmc_api-2.2.1.dist-info/WHEEL
pnap_bmc_api-2.2.1.dist-info/top_level.txt
pnap_bmc_api-2.2.1.dist-info/RECORD
